gitdb/__init__.py
gitdb/exceptions.py
gitdb/gitdb.py
gitdb/serializers/__init__.py
gitdb/serializers/baseserializer.py
gitdb/serializers/bjsonserializer.py
gitdb/serializers/jsonserializer.py
gitdb/serializers/msgpackserializer.py
gitdb/serializers/yamlserializer.py
python_gitdb-0.0.4.dist-info/LICENSE.txt
python_gitdb-0.0.4.dist-info/METADATA
python_gitdb-0.0.4.dist-info/WHEEL
python_gitdb-0.0.4.dist-info/RECORD
