Metadata-Version: 2.1
Name: python-gitdb
Version: 0.0.4
Summary: Simple Python module to use git as key-value database.
License: MIT
Author: Ansgar Kellner
Author-email: keans@gmx.de
Requires-Python: >=3.9,<4.0
Classifier: License :: OSI Approved :: MIT License
Classifier: Programming Language :: Python :: 3
Classifier: Programming Language :: Python :: 3.9
Classifier: Programming Language :: Python :: 3.10
Classifier: Programming Language :: Python :: 3.11
Classifier: Programming Language :: Python :: 3.12
Requires-Dist: pygit2 (>=1.13.3,<2.0.0)
